{"area": "E09000028", "name": "Southwark", "type": "Upper Tier Local Authority", "priority2018": {"Highest": [{"Measure": "Workplace safety", "highestRank": 1, "highestRankType": "Rank", "Index level": "Indicator", "Domain": "Healthy Lives", "Subdomain": "Working conditions", "Indicator": "Workplace safety", "value": 136.1, "Change1year": -11.2, "Change3year": -2.0}, {"Measure": "Working conditions", "highestRank": 1, "highestRankType": "Rank", "Index level": "Subdomain", "Domain": "Healthy Lives", "Subdomain": "Working conditions", "Indicator": "NaN", "value": 123.8, "Change1year": -3.6, "Change3year": 0.1}, {"Measure": "Public green space", "highestRank": 2, "highestRankType": "Rank", "Index level": "Indicator", "Domain": "Healthy Places", "Subdomain": "Access to green space", "Indicator": "Public green space", "value": 122.2, "Change1year": 0.0, "Change3year": 0.0}, {"Measure": "Suicides", "highestRank": 2, "highestRankType": "Change3year Rank", "Index level": "Indicator", "Domain": "Healthy People", "Subdomain": "Mental health", "Indicator": "Suicides", "value": 120.8, "Change1year": 12.3, "Change3year": 25.4}, {"Measure": "Physical health conditions", "highestRank": 2, "highestRankType": "Change1year Rank", "Index level": "Subdomain", "Domain": "Healthy People", "Subdomain": "Physical health conditions", "Indicator": "NaN", "value": 118.2, "Change1year": 0.1, "Change3year": -1.2}, {"Measure": "Dementia", "highestRank": 2, "highestRankType": "Change1year Rank", "Index level": "Indicator", "Domain": "Healthy People", "Subdomain": "Physical health conditions", "Indicator": "Dementia", "value": 124.6, "Change1year": 3.2, "Change3year": 3.8}, {"Measure": "Cardiovascular conditions", "highestRank": 3, "highestRankType": "Change1year Rank", "Index level": "Indicator", "Domain": "Healthy People", "Subdomain": "Physical health conditions", "Indicator": "Cardiovascular conditions", "value": 121.8, "Change1year": 0.6, "Change3year": 0.5}, {"Measure": "Overweight and obesity in children", "highestRank": 4, "highestRankType": "Change3year Rank", "Index level": "Indicator", "Domain": "Healthy Lives", "Subdomain": "Risk factors for children", "Indicator": "Overweight and obesity in children", "value": 80.9, "Change1year": 8.7, "Change3year": 9.4}, {"Measure": "Infant mortality", "highestRank": 4, "highestRankType": "Change1year Rank", "Index level": "Indicator", "Domain": "Healthy Lives", "Subdomain": "Risk factors for children", "Indicator": "Infant mortality", "value": 109.5, "Change1year": 10.3, "Change3year": 12.6}, {"Measure": "Mortality", "highestRank": 4, "highestRankType": "Change3year Rank", "Index level": "Subdomain", "Domain": "Healthy People", "Subdomain": "Mortality", "Indicator": "NaN", "value": 100.2, "Change1year": -2.2, "Change3year": 7.7}, {"Measure": "Healthy life expectancy", "highestRank": 4, "highestRankType": "Change3year Rank", "Index level": "Indicator", "Domain": "Healthy People", "Subdomain": "Mortality", "Indicator": "Healthy life expectancy", "value": 103.1, "Change1year": -6.2, "Change3year": 11.6}, {"Measure": "Children's social, emotional and mental heath", "highestRank": 5, "highestRankType": "Change1year Rank", "Index level": "Indicator", "Domain": "Healthy Lives", "Subdomain": "Risk factors for children", "Indicator": "Children's social, emotional and mental heath", "value": 96.8, "Change1year": 4.1, "Change3year": 8.4}, {"Measure": "Physiological risk factors", "highestRank": 5, "highestRankType": "Change1year Rank", "Index level": "Subdomain", "Domain": "Healthy Lives", "Subdomain": "Physiological risk factors", "Indicator": "NaN", "value": 114.0, "Change1year": 5.2, "Change3year": -3.1}, {"Measure": "Overweight and obesity in adults", "highestRank": 5, "highestRankType": "Change1year Rank", "Index level": "Indicator", "Domain": "Healthy Lives", "Subdomain": "Physiological risk factors", "Indicator": "Overweight and obesity in adults", "value": 120.3, "Change1year": 13.9, "Change3year": -4.6}, {"Measure": "Distance to sports or leisure facilities", "highestRank": 6, "highestRankType": "Rank", "Index level": "Indicator", "Domain": "Healthy Places", "Subdomain": "Access to services", "Indicator": "Distance to sports or leisure facilities", "value": 120.6, "Change1year": 0.0, "Change3year": 0.0}, {"Measure": "Musculoskeletal conditions", "highestRank": 7, "highestRankType": "Rank", "Index level": "Indicator", "Domain": "Healthy People", "Subdomain": "Physical health conditions", "Indicator": "Musculoskeletal conditions", "value": 114.1, "Change1year": 0.0, "Change3year": -6.5}, {"Measure": "Physical activity", "highestRank": 8, "highestRankType": "Rank", "Index level": "Indicator", "Domain": "Healthy Lives", "Subdomain": "Behavioural risk factors", "Indicator": "Physical activity", "value": 119.5, "Change1year": 12.1, "Change3year": 15.2}, {"Measure": "Access to services", "highestRank": 8, "highestRankType": "Rank", "Index level": "Subdomain", "Domain": "Healthy Places", "Subdomain": "Access to services", "Indicator": "NaN", "value": 117.9, "Change1year": 0.0, "Change3year": 0.2}, {"Measure": "Low pay", "highestRank": 9, "highestRankType": "Rank", "Index level": "Indicator", "Domain": "Healthy Lives", "Subdomain": "Working conditions", "Indicator": "Low pay", "value": 118.3, "Change1year": -0.3, "Change3year": -0.5}, {"Measure": "Kidney disease", "highestRank": 10, "highestRankType": "Rank", "Index level": "Indicator", "Domain": "Healthy People", "Subdomain": "Physical health conditions", "Indicator": "Kidney disease", "value": 117.7, "Change1year": 0.5, "Change3year": -0.1}], "Lowest": [{"Measure": "Workplace safety", "lowestRank": 2, "lowestRankType": "Change1year Rank", "Index level": "Indicator", "Domain": "Healthy Lives", "Subdomain": "Working conditions", "Indicator": "Workplace safety", "value": 136.1, "Change1year": -11.2, "Change3year": -2.0}, {"Measure": "Life worthwhileness", "lowestRank": 3, "lowestRankType": "Rank", "Index level": "Indicator", "Domain": "Healthy People", "Subdomain": "Personal well-being", "Indicator": "Life worthwhileness", "value": 76.3, "Change1year": -10.3, "Change3year": -11.0}, {"Measure": "Sexual health", "lowestRank": 3, "lowestRankType": "Rank", "Index level": "Indicator", "Domain": "Healthy Lives", "Subdomain": "Protective measures", "Indicator": "Sexual health", "value": 76.6, "Change1year": -1.0, "Change3year": -0.1}, {"Measure": "Life satisfaction", "lowestRank": 3, "lowestRankType": "Rank", "Index level": "Indicator", "Domain": "Healthy People", "Subdomain": "Personal well-being", "Indicator": "Life satisfaction", "value": 81.6, "Change1year": -7.7, "Change3year": -8.9}, {"Measure": "Personal well-being", "lowestRank": 3, "lowestRankType": "Rank", "Index level": "Subdomain", "Domain": "Healthy People", "Subdomain": "Personal well-being", "Indicator": "NaN", "value": 79.7, "Change1year": -5.8, "Change3year": -9.0}, {"Measure": "Anxiety", "lowestRank": 3, "lowestRankType": "Rank", "Index level": "Indicator", "Domain": "Healthy People", "Subdomain": "Personal well-being", "Indicator": "Anxiety", "value": 70.3, "Change1year": 2.5, "Change3year": -12.6}, {"Measure": "Low birth weight", "lowestRank": 4, "lowestRankType": "Change3year Rank", "Index level": "Indicator", "Domain": "Healthy Lives", "Subdomain": "Risk factors for children", "Indicator": "Low birth weight", "value": 89.7, "Change1year": -3.6, "Change3year": -16.0}, {"Measure": "Healthy Places", "lowestRank": 4, "lowestRankType": "Rank", "Index level": "Domain", "Domain": "Healthy Places", "Subdomain": "NaN", "Indicator": "NaN", "value": 90.3, "Change1year": -0.9, "Change3year": -2.2}, {"Measure": "Private outdoor space", "lowestRank": 4, "lowestRankType": "Rank", "Index level": "Indicator", "Domain": "Healthy Places", "Subdomain": "Access to green space", "Indicator": "Private outdoor space", "value": 64.5, "Change1year": 0.0, "Change3year": 0.0}, {"Measure": "Happiness", "lowestRank": 4, "lowestRankType": "Rank", "Index level": "Indicator", "Domain": "Healthy People", "Subdomain": "Personal well-being", "Indicator": "Happiness", "value": 87.0, "Change1year": -3.9, "Change3year": -4.6}, {"Measure": "Local environment", "lowestRank": 4, "lowestRankType": "Change3year Rank", "Index level": "Subdomain", "Domain": "Healthy Places", "Subdomain": "Local environment", "Indicator": "NaN", "value": 76.1, "Change1year": -0.9, "Change3year": -3.6}, {"Measure": "Road safety", "lowestRank": 4, "lowestRankType": "Change3year Rank", "Index level": "Indicator", "Domain": "Healthy Places", "Subdomain": "Local environment", "Indicator": "Road safety", "value": 73.9, "Change1year": -0.5, "Change3year": -2.8}, {"Measure": "Healthy life expectancy", "lowestRank": 5, "lowestRankType": "Change1year Rank", "Index level": "Indicator", "Domain": "Healthy People", "Subdomain": "Mortality", "Indicator": "Healthy life expectancy", "value": 103.1, "Change1year": -6.2, "Change3year": 11.6}, {"Measure": "Neighbourhood noise", "lowestRank": 5, "lowestRankType": "Rank", "Index level": "Indicator", "Domain": "Healthy Places", "Subdomain": "Local environment", "Indicator": "Neighbourhood noise", "value": 68.0, "Change1year": -2.7, "Change3year": -9.6}, {"Measure": "Access to green space", "lowestRank": 8, "lowestRankType": "Rank", "Index level": "Subdomain", "Domain": "Healthy Places", "Subdomain": "Access to green space", "Indicator": "NaN", "value": 93.3, "Change1year": 0.0, "Change3year": 0.0}, {"Measure": "Household overcrowding", "lowestRank": 8, "lowestRankType": "Rank", "Index level": "Indicator", "Domain": "Healthy Places", "Subdomain": "Access to housing", "Indicator": "Household overcrowding", "value": 82.9, "Change1year": 0.0, "Change3year": 0.0}, {"Measure": "Access to housing", "lowestRank": 8, "lowestRankType": "Rank", "Index level": "Subdomain", "Domain": "Healthy Places", "Subdomain": "Access to housing", "Indicator": "NaN", "value": 82.9, "Change1year": 0.5, "Change3year": -1.9}, {"Measure": "Mortality", "lowestRank": 9, "lowestRankType": "Change1year Rank", "Index level": "Subdomain", "Domain": "Healthy People", "Subdomain": "Mortality", "Indicator": "NaN", "value": 100.2, "Change1year": -2.2, "Change3year": 7.7}, {"Measure": "Transport noise", "lowestRank": 10, "lowestRankType": "Rank", "Index level": "Indicator", "Domain": "Healthy Places", "Subdomain": "Local environment", "Indicator": "Transport noise", "value": 80.7, "Change1year": 0.0, "Change3year": 0.0}, {"Measure": "Road traffic volume", "lowestRank": 10, "lowestRankType": "Rank", "Index level": "Indicator", "Domain": "Healthy Places", "Subdomain": "Local environment", "Indicator": "Road traffic volume", "value": 82.7, "Change1year": -0.3, "Change3year": -1.3}]}, "data": {"Overall": {"total": {"2015": {"value": 99.8, "Rank": 66, "Change1year": "NaN", "Change3year": "NaN", "Change1year Rank": "NaN", "Change3year Rank": "NaN"}, "2016": {"value": 100.1, "Rank": 63, "Change1year": 0.3, "Change3year": "NaN", "Change1year Rank": 57, "Change3year Rank": "NaN"}, "2017": {"value": 100.4, "Rank": 58, "Change1year": 0.3, "Change3year": "NaN", "Change1year Rank": 35, "Change3year Rank": "NaN"}, "2018": {"value": 99.3, "Rank": 70, "Change1year": -1.1, "Change3year": -0.5, "Change1year Rank": 123, "Change3year Rank": 75}}, "subdomains": {}}, "Healthy Lives": {"total": {"2015": {"value": 102.7, "Rank": 37, "Change1year": "NaN", "Change3year": "NaN", "Change1year Rank": "NaN", "Change3year Rank": "NaN"}, "2016": {"value": 104.0, "Rank": 39, "Change1year": 1.3, "Change3year": "NaN", "Change1year Rank": 64, "Change3year Rank": "NaN"}, "2017": {"value": 103.8, "Rank": 46, "Change1year": -0.2, "Change3year": "NaN", "Change1year Rank": 103, "Change3year Rank": "NaN"}, "2018": {"value": 103.8, "Rank": 39, "Change1year": 0.0, "Change3year": 1.1, "Change1year Rank": "NaN", "Change3year Rank": 86}}, "subdomains": {"Physiological risk factors": {"total": {}, "indicators": {"Diabetes": {"2015": {"value": 108.0, "Rank": 29, "Change1year": "NaN", "Change3year": "NaN", "Change1year Rank": "NaN", "Change3year Rank": "NaN"}, "2016": {"value": 104.0, "Rank": 38, "Change1year": -4.0, "Change3year": "NaN", "Change1year Rank": 145, "Change3year Rank": "NaN"}, "2017": {"value": 104.3, "Rank": 33, "Change1year": 0.3, "Change3year": "NaN", "Change1year Rank": 16, "Change3year Rank": "NaN"}, "2018": {"value": 103.3, "Rank": 31, "Change1year": -1.0, "Change3year": -4.7, "Change1year Rank": 40, "Change3year Rank": 78}}, "Hypertension": {"2015": {"value": 115.9, "Rank": 16, "Change1year": "NaN", "Change3year": "NaN", "Change1year Rank": "NaN", "Change3year Rank": "NaN"}, "2016": {"value": 115.3, "Rank": 19, "Change1year": -0.6, "Change3year": "NaN", "Change1year Rank": 90, "Change3year Rank": "NaN"}, "2017": {"value": 115.6, "Rank": 19, "Change1year": 0.3, "Change3year": "NaN", "Change1year Rank": 31, "Change3year Rank": "NaN"}, "2018": {"value": 116.0, "Rank": 16, "Change1year": 0.4, "Change3year": 0.1, "Change1year Rank": 28, "Change3year Rank": 38}}, "Overweight and obesity in adults": {"2015": {"value": 124.9, "Rank": 3, "Change1year": "NaN", "Change3year": "NaN", "Change1year Rank": "NaN", "Change3year Rank": "NaN"}, "2016": {"value": 124.9, "Rank": 3, "Change1year": 0.0, "Change3year": "NaN", "Change1year Rank": "NaN", "Change3year Rank": "NaN"}, "2017": {"value": 106.4, "Rank": 39, "Change1year": -18.5, "Change3year": "NaN", "Change1year Rank": 147, "Change3year Rank": "NaN"}, "2018": {"value": 120.3, "Rank": 10, "Change1year": 13.9, "Change3year": -4.6, "Change1year Rank": 5, "Change3year Rank": 97}}}}, "Behavioural risk factors": {"total": {}, "indicators": {"Alcohol misuse": {"2015": {"value": 105.4, "Rank": 41, "Change1year": "NaN", "Change3year": "NaN", "Change1year Rank": "NaN", "Change3year Rank": "NaN"}, "2016": {"value": 106.5, "Rank": 42, "Change1year": 1.1, "Change3year": "NaN", "Change1year Rank": 69, "Change3year Rank": "NaN"}, "2017": {"value": 109.2, "Rank": 30, "Change1year": 2.7, "Change3year": "NaN", "Change1year Rank": 27, "Change3year Rank": "NaN"}, "2018": {"value": 106.1, "Rank": 34, "Change1year": -3.1, "Change3year": 0.7, "Change1year Rank": 76, "Change3year Rank": 39}}, "Drug misuse": {"2015": {"value": 100.3, "Rank": 66, "Change1year": "NaN", "Change3year": "NaN", "Change1year Rank": "NaN", "Change3year Rank": "NaN"}, "2016": {"value": 103.4, "Rank": 62, "Change1year": 3.1, "Change3year": "NaN", "Change1year Rank": 67, "Change3year Rank": "NaN"}, "2017": {"value": 100.6, "Rank": 58, "Change1year": -2.8, "Change3year": "NaN", "Change1year Rank": 69, "Change3year Rank": "NaN"}, "2018": {"value": 101.9, "Rank": 53, "Change1year": 1.3, "Change3year": 1.6, "Change1year Rank": 47, "Change3year Rank": 52}}, "Healthy eating": {"2015": {"value": 102.8, "Rank": 53, "Change1year": "NaN", "Change3year": "NaN", "Change1year Rank": "NaN", "Change3year Rank": "NaN"}, "2016": {"value": 102.8, "Rank": 53, "Change1year": 0.0, "Change3year": "NaN", "Change1year Rank": "NaN", "Change3year Rank": "NaN"}, "2017": {"value": 105.3, "Rank": 46, "Change1year": 2.5, "Change3year": "NaN", "Change1year Rank": 67, "Change3year Rank": "NaN"}, "2018": {"value": 86.5, "Rank": 110, "Change1year": -18.8, "Change3year": -16.3, "Change1year Rank": 133, "Change3year Rank": 136}}, "Physical activity": {"2015": {"value": 104.3, "Rank": 47, "Change1year": "NaN", "Change3year": "NaN", "Change1year Rank": "NaN", "Change3year Rank": "NaN"}, "2016": {"value": 104.3, "Rank": 47, "Change1year": 0.0, "Change3year": "NaN", "Change1year Rank": "NaN", "Change3year Rank": "NaN"}, "2017": {"value": 107.4, "Rank": 34, "Change1year": 3.1, "Change3year": "NaN", "Change1year Rank": 43, "Change3year Rank": "NaN"}, "2018": {"value": 119.5, "Rank": 8, "Change1year": 12.1, "Change3year": 15.2, "Change1year Rank": 14, "Change3year Rank": 8}}, "Smoking": {"2015": {"value": 103.6, "Rank": 49, "Change1year": "NaN", "Change3year": "NaN", "Change1year Rank": "NaN", "Change3year Rank": "NaN"}, "2016": {"value": 105.7, "Rank": 62, "Change1year": 2.1, "Change3year": "NaN", "Change1year Rank": 97, "Change3year Rank": "NaN"}, "2017": {"value": 116.6, "Rank": 22, "Change1year": 10.9, "Change3year": "NaN", "Change1year Rank": 19, "Change3year Rank": "NaN"}, "2018": {"value": 108.6, "Rank": 73, "Change1year": -8.0, "Change3year": 5.0, "Change1year Rank": 138, "Change3year Rank": 106}}}}, "Unemployment": {"total": {}, "indicators": {"Unemployment": {"2015": {"value": 90.4, "Rank": 113, "Change1year": "NaN", "Change3year": "NaN", "Change1year Rank": "NaN", "Change3year Rank": "NaN"}, "2016": {"value": 91.8, "Rank": 121, "Change1year": 1.4, "Change3year": "NaN", "Change1year Rank": 79, "Change3year Rank": "NaN"}, "2017": {"value": 92.8, "Rank": 132, "Change1year": 1.0, "Change3year": "NaN", "Change1year Rank": 102, "Change3year Rank": "NaN"}, "2018": {"value": 94.3, "Rank": 135, "Change1year": 1.5, "Change3year": 3.9, "Change1year Rank": 78, "Change3year Rank": 107}}}}, "Working conditions": {"total": {}, "indicators": {"Job-related training": {"2015": {"value": 108.7, "Rank": 26, "Change1year": "NaN", "Change3year": "NaN", "Change1year Rank": "NaN", "Change3year Rank": "NaN"}, "2016": {"value": 106.0, "Rank": 34, "Change1year": -2.7, "Change3year": "NaN", "Change1year Rank": 79, "Change3year Rank": "NaN"}, "2017": {"value": 114.0, "Rank": 11, "Change1year": 8.0, "Change3year": "NaN", "Change1year Rank": 15, "Change3year Rank": "NaN"}, "2018": {"value": 115.9, "Rank": 10, "Change1year": 1.9, "Change3year": 7.2, "Change1year Rank": 67, "Change3year Rank": 29}}, "Low pay": {"2015": {"value": 118.8, "Rank": 8, "Change1year": "NaN", "Change3year": "NaN", "Change1year Rank": "NaN", "Change3year Rank": "NaN"}, "2016": {"value": 120.6, "Rank": 4, "Change1year": 1.8, "Change3year": "NaN", "Change1year Rank": 36, "Change3year Rank": "NaN"}, "2017": {"value": 118.6, "Rank": 10, "Change1year": -2.0, "Change3year": "NaN", "Change1year Rank": 117, "Change3year Rank": "NaN"}, "2018": {"value": 118.3, "Rank": 9, "Change1year": -0.3, "Change3year": -0.5, "Change1year Rank": 60, "Change3year Rank": 71}}, "Workplace safety": {"2015": {"value": 138.1, "Rank": 1, "Change1year": "NaN", "Change3year": "NaN", "Change1year Rank": "NaN", "Change3year Rank": "NaN"}, "2016": {"value": 136.7, "Rank": 1, "Change1year": -1.4, "Change3year": "NaN", "Change1year Rank": 115, "Change3year Rank": "NaN"}, "2017": {"value": 147.3, "Rank": 1, "Change1year": 10.6, "Change3year": "NaN", "Change1year Rank": 3, "Change3year Rank": "NaN"}, "2018": {"value": 136.1, "Rank": 1, "Change1year": -11.2, "Change3year": -2.0, "Change1year Rank": 148, "Change3year Rank": 120}}}}, "Risk factors for children": {"total": {}, "indicators": {"Child poverty": {"2015": {"value": 95.9, "Rank": 98, "Change1year": "NaN", "Change3year": "NaN", "Change1year Rank": "NaN", "Change3year Rank": "NaN"}, "2016": {"value": 99.4, "Rank": 82, "Change1year": 3.5, "Change3year": "NaN", "Change1year Rank": 17, "Change3year Rank": "NaN"}, "2017": {"value": 97.2, "Rank": 90, "Change1year": -2.2, "Change3year": "NaN", "Change1year Rank": 122, "Change3year Rank": "NaN"}, "2018": {"value": 97.8, "Rank": 87, "Change1year": 0.6, "Change3year": 1.9, "Change1year Rank": 21, "Change3year Rank": 34}}, "Children in state care": {"2015": {"value": 89.5, "Rank": 118, "Change1year": "NaN", "Change3year": "NaN", "Change1year Rank": "NaN", "Change3year Rank": "NaN"}, "2016": {"value": 91.8, "Rank": 102, "Change1year": 2.3, "Change3year": "NaN", "Change1year Rank": 12, "Change3year Rank": "NaN"}, "2017": {"value": 90.9, "Rank": 101, "Change1year": -0.9, "Change3year": "NaN", "Change1year Rank": 71, "Change3year Rank": "NaN"}, "2018": {"value": 91.5, "Rank": 96, "Change1year": 0.6, "Change3year": 2.0, "Change1year Rank": 31, "Change3year Rank": 28}}, "Children's social, emotional and mental heath": {"2015": {"value": 88.4, "Rank": 125, "Change1year": "NaN", "Change3year": "NaN", "Change1year Rank": "NaN", "Change3year Rank": "NaN"}, "2016": {"value": 93.8, "Rank": 120, "Change1year": 5.4, "Change3year": "NaN", "Change1year Rank": 64, "Change3year Rank": "NaN"}, "2017": {"value": 92.7, "Rank": 128, "Change1year": -1.1, "Change3year": "NaN", "Change1year Rank": 105, "Change3year Rank": "NaN"}, "2018": {"value": 96.8, "Rank": 111, "Change1year": 4.1, "Change3year": 8.4, "Change1year Rank": 5, "Change3year Rank": 32}}, "Infant mortality": {"2015": {"value": 96.9, "Rank": 92, "Change1year": "NaN", "Change3year": "NaN", "Change1year Rank": "NaN", "Change3year Rank": "NaN"}, "2016": {"value": 103.2, "Rank": 62, "Change1year": 6.3, "Change3year": "NaN", "Change1year Rank": 26, "Change3year Rank": "NaN"}, "2017": {"value": 99.2, "Rank": 82, "Change1year": -4.0, "Change3year": "NaN", "Change1year Rank": 109, "Change3year Rank": "NaN"}, "2018": {"value": 109.5, "Rank": 24, "Change1year": 10.3, "Change3year": 12.6, "Change1year Rank": 4, "Change3year Rank": 13}}, "Low birth weight": {"2015": {"value": 105.7, "Rank": 42, "Change1year": "NaN", "Change3year": "NaN", "Change1year Rank": "NaN", "Change3year Rank": "NaN"}, "2016": {"value": 99.6, "Rank": 67, "Change1year": -6.1, "Change3year": "NaN", "Change1year Rank": 119, "Change3year Rank": "NaN"}, "2017": {"value": 93.3, "Rank": 107, "Change1year": -6.3, "Change3year": "NaN", "Change1year Rank": 123, "Change3year Rank": "NaN"}, "2018": {"value": 89.7, "Rank": 113, "Change1year": -3.6, "Change3year": -16.0, "Change1year Rank": 103, "Change3year Rank": 146}}, "Overweight and obesity in children": {"2015": {"value": 71.5, "Rank": 149, "Change1year": "NaN", "Change3year": "NaN", "Change1year Rank": "NaN", "Change3year Rank": "NaN"}, "2016": {"value": 76.6, "Rank": 143, "Change1year": 5.1, "Change3year": "NaN", "Change1year Rank": 5, "Change3year Rank": "NaN"}, "2017": {"value": 72.2, "Rank": 146, "Change1year": -4.4, "Change3year": "NaN", "Change1year Rank": 115, "Change3year Rank": "NaN"}, "2018": {"value": 80.9, "Rank": 134, "Change1year": 8.7, "Change3year": 9.4, "Change1year Rank": 6, "Change3year Rank": 4}}, "Teenage pregnancy": {"2015": {"value": 92.9, "Rank": 99, "Change1year": "NaN", "Change3year": "NaN", "Change1year Rank": "NaN", "Change3year Rank": "NaN"}, "2016": {"value": 91.2, "Rank": 119, "Change1year": -1.7, "Change3year": "NaN", "Change1year Rank": 133, "Change3year Rank": "NaN"}, "2017": {"value": 99.9, "Rank": 96, "Change1year": 8.7, "Change3year": "NaN", "Change1year Rank": 12, "Change3year Rank": "NaN"}, "2018": {"value": 96.6, "Rank": 117, "Change1year": -3.3, "Change3year": 3.7, "Change1year Rank": 130, "Change3year Rank": 108}}}}, "Children and young people's education": {"total": {}, "indicators": {"Early years development": {"2015": {"value": 109.7, "Rank": 22, "Change1year": "NaN", "Change3year": "NaN", "Change1year Rank": "NaN", "Change3year Rank": "NaN"}, "2016": {"value": 113.7, "Rank": 30, "Change1year": 4.0, "Change3year": "NaN", "Change1year Rank": 118, "Change3year Rank": "NaN"}, "2017": {"value": 117.3, "Rank": 33, "Change1year": 3.6, "Change3year": "NaN", "Change1year Rank": 81, "Change3year Rank": "NaN"}, "2018": {"value": 122.3, "Rank": 19, "Change1year": 5.0, "Change3year": 12.6, "Change1year Rank": 21, "Change3year Rank": 82}}, "GCSE achievement": {"2015": {"value": 111.9, "Rank": 18, "Change1year": "NaN", "Change3year": "NaN", "Change1year Rank": "NaN", "Change3year Rank": "NaN"}, "2016": {"value": 119.7, "Rank": 22, "Change1year": 7.8, "Change3year": "NaN", "Change1year Rank": 84, "Change3year Rank": "NaN"}, "2017": {"value": 117.3, "Rank": 34, "Change1year": -2.4, "Change3year": "NaN", "Change1year Rank": 120, "Change3year Rank": "NaN"}, "2018": {"value": 118.9, "Rank": 33, "Change1year": 1.6, "Change3year": 7.0, "Change1year Rank": 69, "Change3year Rank": 122}}, "Pupil absence": {"2015": {"value": 110.2, "Rank": 20, "Change1year": "NaN", "Change3year": "NaN", "Change1year Rank": "NaN", "Change3year Rank": "NaN"}, "2016": {"value": 114.1, "Rank": 18, "Change1year": 3.9, "Change3year": "NaN", "Change1year Rank": 68, "Change3year Rank": "NaN"}, "2017": {"value": 114.0, "Rank": 17, "Change1year": -0.1, "Change3year": "NaN", "Change1year Rank": 49, "Change3year Rank": "NaN"}, "2018": {"value": 107.5, "Rank": 25, "Change1year": -6.5, "Change3year": -2.7, "Change1year Rank": 131, "Change3year Rank": 86}}, "Young people's education, employment and training": {"2015": {"value": 116.0, "Rank": 8, "Change1year": "NaN", "Change3year": "NaN", "Change1year Rank": "NaN", "Change3year Rank": "NaN"}, "2016": {"value": 116.0, "Rank": 8, "Change1year": 0.0, "Change3year": "NaN", "Change1year Rank": "NaN", "Change3year Rank": "NaN"}, "2017": {"value": 113.3, "Rank": 18, "Change1year": -2.7, "Change3year": "NaN", "Change1year Rank": 116, "Change3year Rank": "NaN"}, "2018": {"value": 113.3, "Rank": 20, "Change1year": 0.0, "Change3year": -2.7, "Change1year Rank": "NaN", "Change3year Rank": 117}}}}, "Protective measures": {"total": {}, "indicators": {"Cancer screening": {"2015": {"value": 82.4, "Rank": 137, "Change1year": "NaN", "Change3year": "NaN", "Change1year Rank": "NaN", "Change3year Rank": "NaN"}, "2016": {"value": 81.3, "Rank": 137, "Change1year": -1.1, "Change3year": "NaN", "Change1year Rank": 110, "Change3year Rank": "NaN"}, "2017": {"value": 81.4, "Rank": 137, "Change1year": 0.1, "Change3year": "NaN", "Change1year Rank": 46, "Change3year Rank": "NaN"}, "2018": {"value": 80.9, "Rank": 138, "Change1year": -0.5, "Change3year": -1.5, "Change1year Rank": 45, "Change3year Rank": 70}}, "Sexual health": {"2015": {"value": 76.7, "Rank": 148, "Change1year": "NaN", "Change3year": "NaN", "Change1year Rank": "NaN", "Change3year Rank": "NaN"}, "2016": {"value": 77.3, "Rank": 147, "Change1year": 0.6, "Change3year": "NaN", "Change1year Rank": 87, "Change3year Rank": "NaN"}, "2017": {"value": 77.6, "Rank": 147, "Change1year": 0.3, "Change3year": "NaN", "Change1year Rank": 74, "Change3year Rank": "NaN"}, "2018": {"value": 76.6, "Rank": 147, "Change1year": -1.0, "Change3year": -0.1, "Change1year Rank": 74, "Change3year Rank": 75}}, "Vaccination coverage": {"2015": {"value": 85.5, "Rank": 136, "Change1year": "NaN", "Change3year": "NaN", "Change1year Rank": "NaN", "Change3year Rank": "NaN"}, "2016": {"value": 90.9, "Rank": 115, "Change1year": 5.4, "Change3year": "NaN", "Change1year Rank": 4, "Change3year Rank": "NaN"}, "2017": {"value": 90.3, "Rank": 112, "Change1year": -0.6, "Change3year": "NaN", "Change1year Rank": 70, "Change3year Rank": "NaN"}, "2018": {"value": 84.0, "Rank": 126, "Change1year": -6.3, "Change3year": -1.5, "Change1year Rank": 140, "Change3year Rank": 53}}}}}}, "Healthy People": {"total": {"2015": {"value": 104.2, "Rank": 37, "Change1year": "NaN", "Change3year": "NaN", "Change1year Rank": "NaN", "Change3year Rank": "NaN"}, "2016": {"value": 104.4, "Rank": 38, "Change1year": 0.2, "Change3year": "NaN", "Change1year Rank": 51, "Change3year Rank": "NaN"}, "2017": {"value": 106.1, "Rank": 22, "Change1year": 1.7, "Change3year": "NaN", "Change1year Rank": 13, "Change3year Rank": "NaN"}, "2018": {"value": 103.9, "Rank": 39, "Change1year": -2.2, "Change3year": -0.3, "Change1year Rank": 128, "Change3year Rank": 52}}, "subdomains": {"Mortality": {"total": {}, "indicators": {"Avoidable deaths": {"2015": {"value": 93.6, "Rank": 90, "Change1year": "NaN", "Change3year": "NaN", "Change1year Rank": "NaN", "Change3year Rank": "NaN"}, "2016": {"value": 93.5, "Rank": 96, "Change1year": -0.1, "Change3year": "NaN", "Change1year Rank": 85, "Change3year Rank": "NaN"}, "2017": {"value": 95.5, "Rank": 88, "Change1year": 2.0, "Change3year": "NaN", "Change1year Rank": 21, "Change3year Rank": "NaN"}, "2018": {"value": 97.4, "Rank": 82, "Change1year": 1.9, "Change3year": 3.8, "Change1year Rank": 21, "Change3year Rank": 19}}, "Healthy life expectancy": {"2015": {"value": 91.5, "Rank": 107, "Change1year": "NaN", "Change3year": "NaN", "Change1year Rank": "NaN", "Change3year Rank": "NaN"}, "2016": {"value": 95.4, "Rank": 87, "Change1year": 3.9, "Change3year": "NaN", "Change1year Rank": 17, "Change3year Rank": "NaN"}, "2017": {"value": 109.3, "Rank": 18, "Change1year": 13.9, "Change3year": "NaN", "Change1year Rank": 2, "Change3year Rank": "NaN"}, "2018": {"value": 103.1, "Rank": 51, "Change1year": -6.2, "Change3year": 11.6, "Change1year Rank": 145, "Change3year Rank": 4}}}}, "Physical health conditions": {"total": {}, "indicators": {"Cancer": {"2015": {"value": 118.0, "Rank": 9, "Change1year": "NaN", "Change3year": "NaN", "Change1year Rank": "NaN", "Change3year Rank": "NaN"}, "2016": {"value": 117.1, "Rank": 7, "Change1year": -0.9, "Change3year": "NaN", "Change1year Rank": 4, "Change3year Rank": "NaN"}, "2017": {"value": 115.7, "Rank": 8, "Change1year": -1.4, "Change3year": "NaN", "Change1year Rank": 24, "Change3year Rank": "NaN"}, "2018": {"value": 111.7, "Rank": 10, "Change1year": -4.0, "Change3year": -6.3, "Change1year Rank": 58, "Change3year Rank": 25}}, "Cardiovascular conditions": {"2015": {"value": 121.3, "Rank": 5, "Change1year": "NaN", "Change3year": "NaN", "Change1year Rank": "NaN", "Change3year Rank": "NaN"}, "2016": {"value": 121.2, "Rank": 5, "Change1year": -0.1, "Change3year": "NaN", "Change1year Rank": 23, "Change3year Rank": "NaN"}, "2017": {"value": 121.2, "Rank": 5, "Change1year": 0.0, "Change3year": "NaN", "Change1year Rank": "NaN", "Change3year Rank": "NaN"}, "2018": {"value": 121.8, "Rank": 4, "Change1year": 0.6, "Change3year": 0.5, "Change1year Rank": 3, "Change3year Rank": 7}}, "Dementia": {"2015": {"value": 120.8, "Rank": 8, "Change1year": "NaN", "Change3year": "NaN", "Change1year Rank": "NaN", "Change3year Rank": "NaN"}, "2016": {"value": 121.4, "Rank": 5, "Change1year": 0.6, "Change3year": "NaN", "Change1year Rank": 30, "Change3year Rank": "NaN"}, "2017": {"value": 121.4, "Rank": 5, "Change1year": 0.0, "Change3year": "NaN", "Change1year Rank": "NaN", "Change3year Rank": "NaN"}, "2018": {"value": 124.6, "Rank": 3, "Change1year": 3.2, "Change3year": 3.8, "Change1year Rank": 2, "Change3year Rank": 4}}, "Kidney disease": {"2015": {"value": 117.8, "Rank": 11, "Change1year": "NaN", "Change3year": "NaN", "Change1year Rank": "NaN", "Change3year Rank": "NaN"}, "2016": {"value": 116.9, "Rank": 11, "Change1year": -0.9, "Change3year": "NaN", "Change1year Rank": 108, "Change3year Rank": "NaN"}, "2017": {"value": 117.2, "Rank": 11, "Change1year": 0.3, "Change3year": "NaN", "Change1year Rank": 72, "Change3year Rank": "NaN"}, "2018": {"value": 117.7, "Rank": 10, "Change1year": 0.5, "Change3year": -0.1, "Change1year Rank": 50, "Change3year Rank": 81}}, "Musculoskeletal conditions": {"2015": {"value": 120.6, "Rank": 11, "Change1year": "NaN", "Change3year": "NaN", "Change1year Rank": "NaN", "Change3year Rank": "NaN"}, "2016": {"value": 114.8, "Rank": 13, "Change1year": -5.8, "Change3year": "NaN", "Change1year Rank": 68, "Change3year Rank": "NaN"}, "2017": {"value": 114.1, "Rank": 11, "Change1year": -0.7, "Change3year": "NaN", "Change1year Rank": 16, "Change3year Rank": "NaN"}, "2018": {"value": 114.1, "Rank": 7, "Change1year": 0.0, "Change3year": -6.5, "Change1year Rank": "NaN", "Change3year Rank": 13}}, "Respiratory conditions": {"2015": {"value": 117.7, "Rank": 16, "Change1year": "NaN", "Change3year": "NaN", "Change1year Rank": "NaN", "Change3year Rank": "NaN"}, "2016": {"value": 116.7, "Rank": 19, "Change1year": -1.0, "Change3year": "NaN", "Change1year Rank": 86, "Change3year Rank": "NaN"}, "2017": {"value": 117.8, "Rank": 17, "Change1year": 1.1, "Change3year": "NaN", "Change1year Rank": 17, "Change3year Rank": "NaN"}, "2018": {"value": 117.8, "Rank": 16, "Change1year": 0.0, "Change3year": 0.1, "Change1year Rank": "NaN", "Change3year Rank": 20}}}}, "Difficulties in daily life": {"total": {}, "indicators": {"Difficulty completing Activities of Daily Living (ADLs)": {"2015": {"value": 114.4, "Rank": 12, "Change1year": "NaN", "Change3year": "NaN", "Change1year Rank": "NaN", "Change3year Rank": "NaN"}, "2016": {"value": 114.4, "Rank": 12, "Change1year": 0.0, "Change3year": "NaN", "Change1year Rank": "NaN", "Change3year Rank": "NaN"}, "2017": {"value": 114.4, "Rank": 12, "Change1year": 0.0, "Change3year": "NaN", "Change1year Rank": "NaN", "Change3year Rank": "NaN"}, "2018": {"value": 114.4, "Rank": 12, "Change1year": 0.0, "Change3year": 0.0, "Change1year Rank": "NaN", "Change3year Rank": "NaN"}}, "Disability that impacts daily activities": {"2015": {"value": 107.7, "Rank": 37, "Change1year": "NaN", "Change3year": "NaN", "Change1year Rank": "NaN", "Change3year Rank": "NaN"}, "2016": {"value": 122.4, "Rank": 4, "Change1year": 14.7, "Change3year": "NaN", "Change1year Rank": 2, "Change3year Rank": "NaN"}, "2017": {"value": 120.4, "Rank": 3, "Change1year": -2.0, "Change3year": "NaN", "Change1year Rank": 87, "Change3year Rank": "NaN"}, "2018": {"value": 108.3, "Rank": 22, "Change1year": -12.1, "Change3year": 0.6, "Change1year Rank": 128, "Change3year Rank": 43}}, "Frailty": {"2015": {"value": 106.1, "Rank": 41, "Change1year": "NaN", "Change3year": "NaN", "Change1year Rank": "NaN", "Change3year Rank": "NaN"}, "2016": {"value": 116.2, "Rank": 12, "Change1year": 10.1, "Change3year": "NaN", "Change1year Rank": 19, "Change3year Rank": "NaN"}, "2017": {"value": 109.3, "Rank": 28, "Change1year": -6.9, "Change3year": "NaN", "Change1year Rank": 119, "Change3year Rank": "NaN"}, "2018": {"value": 111.9, "Rank": 27, "Change1year": 2.6, "Change3year": 5.8, "Change1year Rank": 75, "Change3year Rank": 63}}}}, "Personal well-being": {"total": {}, "indicators": {"Anxiety": {"2015": {"value": 82.9, "Rank": 139, "Change1year": "NaN", "Change3year": "NaN", "Change1year Rank": "NaN", "Change3year Rank": "NaN"}, "2016": {"value": 79.1, "Rank": 142, "Change1year": -3.8, "Change3year": "NaN", "Change1year Rank": 88, "Change3year Rank": "NaN"}, "2017": {"value": 67.8, "Rank": 148, "Change1year": -11.3, "Change3year": "NaN", "Change1year Rank": 135, "Change3year Rank": "NaN"}, "2018": {"value": 70.3, "Rank": 147, "Change1year": 2.5, "Change3year": -12.6, "Change1year Rank": 65, "Change3year Rank": 134}}, "Happiness": {"2015": {"value": 91.6, "Rank": 111, "Change1year": "NaN", "Change3year": "NaN", "Change1year Rank": "NaN", "Change3year Rank": "NaN"}, "2016": {"value": 90.3, "Rank": 124, "Change1year": -1.3, "Change3year": "NaN", "Change1year Rank": 94, "Change3year Rank": "NaN"}, "2017": {"value": 90.9, "Rank": 125, "Change1year": 0.6, "Change3year": "NaN", "Change1year Rank": 81, "Change3year Rank": "NaN"}, "2018": {"value": 87.0, "Rank": 146, "Change1year": -3.9, "Change3year": -4.6, "Change1year Rank": 121, "Change3year Rank": 133}}, "Life satisfaction": {"2015": {"value": 90.5, "Rank": 117, "Change1year": "NaN", "Change3year": "NaN", "Change1year Rank": "NaN", "Change3year Rank": "NaN"}, "2016": {"value": 83.4, "Rank": 142, "Change1year": -7.1, "Change3year": "NaN", "Change1year Rank": 138, "Change3year Rank": "NaN"}, "2017": {"value": 89.3, "Rank": 127, "Change1year": 5.9, "Change3year": "NaN", "Change1year Rank": 38, "Change3year Rank": "NaN"}, "2018": {"value": 81.6, "Rank": 147, "Change1year": -7.7, "Change3year": -8.9, "Change1year Rank": 138, "Change3year Rank": 140}}, "Life worthwhileness": {"2015": {"value": 87.3, "Rank": 126, "Change1year": "NaN", "Change3year": "NaN", "Change1year Rank": "NaN", "Change3year Rank": "NaN"}, "2016": {"value": 82.4, "Rank": 143, "Change1year": -4.9, "Change3year": "NaN", "Change1year Rank": 124, "Change3year Rank": "NaN"}, "2017": {"value": 86.6, "Rank": 131, "Change1year": 4.2, "Change3year": "NaN", "Change1year Rank": 54, "Change3year Rank": "NaN"}, "2018": {"value": 76.3, "Rank": 147, "Change1year": -10.3, "Change3year": -11.0, "Change1year Rank": 138, "Change3year Rank": 142}}}}, "Mental health": {"total": {}, "indicators": {"Depression": {"2015": {"value": 113.5, "Rank": 22, "Change1year": "NaN", "Change3year": "NaN", "Change1year Rank": "NaN", "Change3year Rank": "NaN"}, "2016": {"value": 106.0, "Rank": 29, "Change1year": -7.5, "Change3year": "NaN", "Change1year Rank": 129, "Change3year Rank": "NaN"}, "2017": {"value": 102.9, "Rank": 25, "Change1year": -3.1, "Change3year": "NaN", "Change1year Rank": 17, "Change3year Rank": "NaN"}, "2018": {"value": 98.6, "Rank": 26, "Change1year": -4.3, "Change3year": -14.9, "Change1year Rank": 46, "Change3year Rank": 62}}, "Self-harm": {"2015": {"value": 116.3, "Rank": 18, "Change1year": "NaN", "Change3year": "NaN", "Change1year Rank": "NaN", "Change3year Rank": "NaN"}, "2016": {"value": 114.3, "Rank": 31, "Change1year": -2.0, "Change3year": "NaN", "Change1year Rank": 125, "Change3year Rank": "NaN"}, "2017": {"value": 114.2, "Rank": 28, "Change1year": -0.1, "Change3year": "NaN", "Change1year Rank": 72, "Change3year Rank": "NaN"}, "2018": {"value": 110.9, "Rank": 33, "Change1year": -3.3, "Change3year": -5.4, "Change1year Rank": 111, "Change3year Rank": 129}}, "Suicides": {"2015": {"value": 95.4, "Rank": 102, "Change1year": "NaN", "Change3year": "NaN", "Change1year Rank": "NaN", "Change3year Rank": "NaN"}, "2016": {"value": 97.2, "Rank": 97, "Change1year": 1.8, "Change3year": "NaN", "Change1year Rank": 63, "Change3year Rank": "NaN"}, "2017": {"value": 108.5, "Rank": 46, "Change1year": 11.3, "Change3year": "NaN", "Change1year Rank": 6, "Change3year Rank": "NaN"}, "2018": {"value": 120.8, "Rank": 9, "Change1year": 12.3, "Change3year": 25.4, "Change1year Rank": 8, "Change3year Rank": 2}}}}}}, "Healthy Places": {"total": {"2015": {"value": 92.5, "Rank": 143, "Change1year": "NaN", "Change3year": "NaN", "Change1year Rank": "NaN", "Change3year Rank": "NaN"}, "2016": {"value": 91.7, "Rank": 145, "Change1year": -0.8, "Change3year": "NaN", "Change1year Rank": 94, "Change3year Rank": "NaN"}, "2017": {"value": 91.2, "Rank": 145, "Change1year": -0.5, "Change3year": "NaN", "Change1year Rank": 80, "Change3year Rank": "NaN"}, "2018": {"value": 90.3, "Rank": 146, "Change1year": -0.9, "Change3year": -2.2, "Change1year Rank": 123, "Change3year Rank": 121}}, "subdomains": {"Access to green space": {"total": {}, "indicators": {"Private outdoor space": {"2015": {"value": 64.5, "Rank": 146, "Change1year": "NaN", "Change3year": "NaN", "Change1year Rank": "NaN", "Change3year Rank": "NaN"}, "2016": {"value": 64.5, "Rank": 146, "Change1year": 0.0, "Change3year": "NaN", "Change1year Rank": "NaN", "Change3year Rank": "NaN"}, "2017": {"value": 64.5, "Rank": 146, "Change1year": 0.0, "Change3year": "NaN", "Change1year Rank": "NaN", "Change3year Rank": "NaN"}, "2018": {"value": 64.5, "Rank": 146, "Change1year": 0.0, "Change3year": 0.0, "Change1year Rank": "NaN", "Change3year Rank": "NaN"}}, "Public green space": {"2015": {"value": 122.2, "Rank": 2, "Change1year": "NaN", "Change3year": "NaN", "Change1year Rank": "NaN", "Change3year Rank": "NaN"}, "2016": {"value": 122.2, "Rank": 2, "Change1year": 0.0, "Change3year": "NaN", "Change1year Rank": "NaN", "Change3year Rank": "NaN"}, "2017": {"value": 122.2, "Rank": 2, "Change1year": 0.0, "Change3year": "NaN", "Change1year Rank": "NaN", "Change3year Rank": "NaN"}, "2018": {"value": 122.2, "Rank": 2, "Change1year": 0.0, "Change3year": 0.0, "Change1year Rank": "NaN", "Change3year Rank": "NaN"}}}}, "Local environment": {"total": {}, "indicators": {"Air pollution": {"2015": {"value": 79.2, "Rank": 143, "Change1year": "NaN", "Change3year": "NaN", "Change1year Rank": "NaN", "Change3year Rank": "NaN"}, "2016": {"value": 76.6, "Rank": 140, "Change1year": -2.6, "Change3year": "NaN", "Change1year Rank": 53, "Change3year Rank": "NaN"}, "2017": {"value": 74.8, "Rank": 140, "Change1year": -1.8, "Change3year": "NaN", "Change1year Rank": 134, "Change3year Rank": "NaN"}, "2018": {"value": 73.9, "Rank": 140, "Change1year": -0.9, "Change3year": -5.3, "Change1year Rank": 65, "Change3year Rank": 101}}, "Neighbourhood noise": {"2015": {"value": 77.6, "Rank": 140, "Change1year": "NaN", "Change3year": "NaN", "Change1year Rank": "NaN", "Change3year Rank": "NaN"}, "2016": {"value": 73.8, "Rank": 142, "Change1year": -3.8, "Change3year": "NaN", "Change1year Rank": 145, "Change3year Rank": "NaN"}, "2017": {"value": 70.7, "Rank": 144, "Change1year": -3.1, "Change3year": "NaN", "Change1year Rank": 145, "Change3year Rank": "NaN"}, "2018": {"value": 68.0, "Rank": 145, "Change1year": -2.7, "Change3year": -9.6, "Change1year Rank": 145, "Change3year Rank": 145}}, "Road safety": {"2015": {"value": 76.7, "Rank": 141, "Change1year": "NaN", "Change3year": "NaN", "Change1year Rank": "NaN", "Change3year Rank": "NaN"}, "2016": {"value": 75.4, "Rank": 142, "Change1year": -1.3, "Change3year": "NaN", "Change1year Rank": 140, "Change3year Rank": "NaN"}, "2017": {"value": 74.4, "Rank": 143, "Change1year": -1.0, "Change3year": "NaN", "Change1year Rank": 124, "Change3year Rank": "NaN"}, "2018": {"value": 73.9, "Rank": 144, "Change1year": -0.5, "Change3year": -2.8, "Change1year Rank": 141, "Change3year Rank": 146}}, "Road traffic volume": {"2015": {"value": 84.0, "Rank": 139, "Change1year": "NaN", "Change3year": "NaN", "Change1year Rank": "NaN", "Change3year Rank": "NaN"}, "2016": {"value": 83.6, "Rank": 138, "Change1year": -0.4, "Change3year": "NaN", "Change1year Rank": 109, "Change3year Rank": "NaN"}, "2017": {"value": 83.0, "Rank": 140, "Change1year": -0.6, "Change3year": "NaN", "Change1year Rank": 131, "Change3year Rank": "NaN"}, "2018": {"value": 82.7, "Rank": 140, "Change1year": -0.3, "Change3year": -1.3, "Change1year Rank": 82, "Change3year Rank": 121}}, "Transport noise": {"2015": {"value": 80.7, "Rank": 140, "Change1year": "NaN", "Change3year": "NaN", "Change1year Rank": "NaN", "Change3year Rank": "NaN"}, "2016": {"value": 80.7, "Rank": 140, "Change1year": 0.0, "Change3year": "NaN", "Change1year Rank": "NaN", "Change3year Rank": "NaN"}, "2017": {"value": 80.7, "Rank": 140, "Change1year": 0.0, "Change3year": "NaN", "Change1year Rank": "NaN", "Change3year Rank": "NaN"}, "2018": {"value": 80.7, "Rank": 140, "Change1year": 0.0, "Change3year": 0.0, "Change1year Rank": "NaN", "Change3year Rank": "NaN"}}}}, "Access to housing": {"total": {}, "indicators": {"Household overcrowding": {"2015": {"value": 82.9, "Rank": 142, "Change1year": "NaN", "Change3year": "NaN", "Change1year Rank": "NaN", "Change3year Rank": "NaN"}, "2016": {"value": 82.9, "Rank": 142, "Change1year": 0.0, "Change3year": "NaN", "Change1year Rank": "NaN", "Change3year Rank": "NaN"}, "2017": {"value": 82.9, "Rank": 142, "Change1year": 0.0, "Change3year": "NaN", "Change1year Rank": "NaN", "Change3year Rank": "NaN"}, "2018": {"value": 82.9, "Rank": 142, "Change1year": 0.0, "Change3year": 0.0, "Change1year Rank": "NaN", "Change3year Rank": "NaN"}}, "Housing affordability": {"2015": {"value": 82.2, "Rank": 138, "Change1year": "NaN", "Change3year": "NaN", "Change1year Rank": "NaN", "Change3year Rank": "NaN"}, "2016": {"value": 79.6, "Rank": 140, "Change1year": -2.6, "Change3year": "NaN", "Change1year Rank": 123, "Change3year Rank": "NaN"}, "2017": {"value": 78.6, "Rank": 140, "Change1year": -1.0, "Change3year": "NaN", "Change1year Rank": 71, "Change3year Rank": "NaN"}, "2018": {"value": 80.2, "Rank": 137, "Change1year": 1.6, "Change3year": -2.0, "Change1year Rank": 14, "Change3year Rank": 66}}, "Rough sleeping": {"2015": {"value": 90.4, "Rank": 124, "Change1year": "NaN", "Change3year": "NaN", "Change1year Rank": "NaN", "Change3year Rank": "NaN"}, "2016": {"value": 90.5, "Rank": 118, "Change1year": 0.1, "Change3year": "NaN", "Change1year Rank": 45, "Change3year Rank": "NaN"}, "2017": {"value": 87.0, "Rank": 119, "Change1year": -3.5, "Change3year": "NaN", "Change1year Rank": 100, "Change3year Rank": "NaN"}, "2018": {"value": 86.3, "Rank": 130, "Change1year": -0.7, "Change3year": -4.1, "Change1year Rank": 83, "Change3year Rank": 75}}}}, "Access to services": {"total": {}, "indicators": {"Distance to GP services": {"2015": {"value": 118.2, "Rank": 8, "Change1year": "NaN", "Change3year": "NaN", "Change1year Rank": "NaN", "Change3year Rank": "NaN"}, "2016": {"value": 118.8, "Rank": 9, "Change1year": 0.6, "Change3year": "NaN", "Change1year Rank": 135, "Change3year Rank": "NaN"}, "2017": {"value": 118.8, "Rank": 9, "Change1year": 0.0, "Change3year": "NaN", "Change1year Rank": "NaN", "Change3year Rank": "NaN"}, "2018": {"value": 118.8, "Rank": 10, "Change1year": 0.0, "Change3year": 0.6, "Change1year Rank": "NaN", "Change3year Rank": 133}}, "Distance to pharmacies": {"2015": {"value": 114.6, "Rank": 9, "Change1year": "NaN", "Change3year": "NaN", "Change1year Rank": "NaN", "Change3year Rank": "NaN"}, "2016": {"value": 114.6, "Rank": 9, "Change1year": 0.0, "Change3year": "NaN", "Change1year Rank": "NaN", "Change3year Rank": "NaN"}, "2017": {"value": 114.6, "Rank": 9, "Change1year": 0.0, "Change3year": "NaN", "Change1year Rank": "NaN", "Change3year Rank": "NaN"}, "2018": {"value": 114.6, "Rank": 10, "Change1year": 0.0, "Change3year": 0.0, "Change1year Rank": "NaN", "Change3year Rank": "NaN"}}, "Distance to sports or leisure facilities": {"2015": {"value": 120.6, "Rank": 6, "Change1year": "NaN", "Change3year": "NaN", "Change1year Rank": "NaN", "Change3year Rank": "NaN"}, "2016": {"value": 120.6, "Rank": 6, "Change1year": 0.0, "Change3year": "NaN", "Change1year Rank": "NaN", "Change3year Rank": "NaN"}, "2017": {"value": 120.6, "Rank": 6, "Change1year": 0.0, "Change3year": "NaN", "Change1year Rank": "NaN", "Change3year Rank": "NaN"}, "2018": {"value": 120.6, "Rank": 6, "Change1year": 0.0, "Change3year": 0.0, "Change1year Rank": "NaN", "Change3year Rank": "NaN"}}}}, "Crime": {"total": {}, "indicators": {"Personal crime": {"2015": {"value": 86.8, "Rank": 135, "Change1year": "NaN", "Change3year": "NaN", "Change1year Rank": "NaN", "Change3year Rank": "NaN"}, "2016": {"value": 85.5, "Rank": 127, "Change1year": -1.3, "Change3year": "NaN", "Change1year Rank": 61, "Change3year Rank": "NaN"}, "2017": {"value": 85.2, "Rank": 116, "Change1year": -0.3, "Change3year": "NaN", "Change1year Rank": 19, "Change3year Rank": "NaN"}, "2018": {"value": 81.5, "Rank": 122, "Change1year": -3.7, "Change3year": -5.3, "Change1year Rank": 131, "Change3year Rank": 74}}}}}}}}